pyencrypt3/__init__.py
pyencrypt3/cmdline.py
pyencrypt3/encrypt_py.py
pyencrypt3/log.py
pyencrypt3-1.0.3.dist-info/LICENSE
pyencrypt3-1.0.3.dist-info/METADATA
pyencrypt3-1.0.3.dist-info/WHEEL
pyencrypt3-1.0.3.dist-info/entry_points.txt
pyencrypt3-1.0.3.dist-info/top_level.txt
pyencrypt3-1.0.3.dist-info/RECORD
