Metadata-Version: 2.1
Name: pyencrypt3
Version: 1.0.3
Summary: python代码一键加密
Author: 刘飞
Author-email: liufei-love@foxmail.com
License: MIT
Classifier: Programming Language :: Python :: 3.12
License-File: LICENSE
Requires-Dist: Cython>=3.0.11
